{"textConfigs":[{"id":1000,"descrip":"/","localTexts":["This is a chair.","这是一把椅子","","これは椅子です","","","","","","","","","","Default Text 1",""],"fontOverrides":[-1,-1,-1,-1,-1,-1,-1,-1,-1,-1,-1,-1,-1,-1,-1]},{"id":1001,"descrip":"/","localTexts":["There are {0} people in my class.","我们班有{0}个人","","{0}人がクラスにいる","","","","","","","","","","Default Text 2",""],"fontOverrides":[-1,-1,-1,-1,-1,-1,-1,-1,-1,-1,-1,-1,-1,-1,-1]},{"id":1002,"descrip":"/","localTexts":["It is {0}:{1} now.","现在是{0}点{1}分","","今は{0}時{1}分です","","","","","","","","","","Default Text 3",""],"fontOverrides":[-1,-1,-1,-1,-1,-1,-1,-1,-1,-1,-1,-1,-1,-1,-1]}],"imageConfigs":[{"id":-1,"descrip":"/","localImages":[{"instanceID":0},{"instanceID":0},{"instanceID":0},{"instanceID":0},{"instanceID":0},{"instanceID":0},{"instanceID":0},{"instanceID":0},{"instanceID":0},{"instanceID":0},{"instanceID":0},{"instanceID":0},{"instanceID":0},{"instanceID":0},{"instanceID":0}]}],"languageSupports":[0,1,3,13]}